LICENSE
LICENSE.gluon-ts
README.md
setup.py
pts/__init__.py
pts/trainer.py
pts/dataset/__init__.py
pts/dataset/loader.py
pts/dataset/repository/__init__.py
pts/dataset/repository/_m5.py
pts/dataset/repository/datasets.py
pts/distributions/__init__.py
pts/distributions/implicit_quantile.py
pts/distributions/piecewise_linear.py
pts/distributions/utils.py
pts/distributions/zero_inflated.py
pts/feature/__init__.py
pts/feature/fourier_date_feature.py
pts/feature/holiday.py
pts/feature/lags.py
pts/model/__init__.py
pts/model/estimator.py
pts/model/utils.py
pts/model/causal_deepar/__init__.py
pts/model/causal_deepar/causal_deepar_estimator.py
pts/model/causal_deepar/causal_deepar_network.py
pts/model/deepar/__init__.py
pts/model/deepar/deepar_estimator.py
pts/model/deepar/deepar_network.py
pts/model/deepvar/__init__.py
pts/model/deepvar/deepvar_estimator.py
pts/model/deepvar/deepvar_network.py
pts/model/lstnet/__init__.py
pts/model/lstnet/lstnet_estimator.py
pts/model/lstnet/lstnet_network.py
pts/model/n_beats/__init__.py
pts/model/n_beats/n_beats_ensemble.py
pts/model/n_beats/n_beats_estimator.py
pts/model/n_beats/n_beats_network.py
pts/model/simple_feedforward/__init__.py
pts/model/simple_feedforward/simple_feedforward_estimator.py
pts/model/simple_feedforward/simple_feedforward_network.py
pts/model/tempflow/__init__.py
pts/model/tempflow/tempflow_estimator.py
pts/model/tempflow/tempflow_network.py
pts/model/tft/__init__.py
pts/model/tft/tft_estimator.py
pts/model/tft/tft_modules.py
pts/model/tft/tft_network.py
pts/model/tft/tft_output.py
pts/model/tft/tft_transform.py
pts/model/time_grad/__init__.py
pts/model/time_grad/epsilon_theta.py
pts/model/time_grad/time_grad_estimator.py
pts/model/time_grad/time_grad_network.py
pts/model/transformer/__init__.py
pts/model/transformer/transformer_estimator.py
pts/model/transformer/transformer_network.py
pts/model/transformer_tempflow/__init__.py
pts/model/transformer_tempflow/transformer_tempflow_estimator.py
pytorchts.egg-info/PKG-INFO
pytorchts.egg-info/SOURCES.txt
pytorchts.egg-info/dependency_links.txt
pytorchts.egg-info/requires.txt
pytorchts.egg-info/top_level.txt
pytorchts.egg-info/zip-safe