Metadata-Version: 2.1
Name: pytorchts
Version: 0.6.0
Summary: PyTorch Probabilistic Time Series Modeling framework
Home-page: https://github.com/zalandoresearch/pytorch-ts
Author: Kashif Rasul
Author-email: kashif.rasul@zalando.de
License: MIT
Platform: UNKNOWN
Requires-Python: >=3.6
License-File: LICENSE
License-File: LICENSE.gluon-ts
